pyfiler/__init__.py
pyfiler/csvfile.py
pyfiler/file.py
pyfiler/jsonfile.py
pyfiler/pyfile.py
PyFiler-1.3.0.dist-info/METADATA
PyFiler-1.3.0.dist-info/WHEEL
PyFiler-1.3.0.dist-info/top_level.txt
PyFiler-1.3.0.dist-info/RECORD
