Metadata-Version: 2.1
Name: PyFiler
Version: 1.3.0
Summary: A file wrapper and API for python, supports most common files.
Home-page: UNKNOWN
Author: UNKNOWN
Author-email: UNKNOWN
License: UNKNOWN
Platform: UNKNOWN
Requires-Dist: pysheets
